Screenshot/Screenshot.py
Screenshot/__init__.py
selenium_screenshot-3.0.0.dist-info/licenses/LICENSE
test/__init__.py
test/test_screenshot.py
selenium_screenshot-3.0.0.dist-info/METADATA
selenium_screenshot-3.0.0.dist-info/WHEEL
selenium_screenshot-3.0.0.dist-info/top_level.txt
selenium_screenshot-3.0.0.dist-info/RECORD
