Metadata-Version: 2.4
Name: Selenium-Screenshot
Version: 3.0.0
Summary: This package is used to Clipped Images of Html Elements of Selenium Webdriver
Home-page: https://github.com/PyWizards/Selenium_Screenshot
Author: PyWizard org
Author-email: py.wizard.org@gmail.com
License: MIT
Platform: any
Classifier: License :: OSI Approved :: MIT License
Classifier: Programming Language :: Python :: 3
Classifier: Programming Language :: Python :: 3.8
Requires-Python: >=3.6.1
License-File: LICENSE
Requires-Dist: Pillow
Requires-Dist: selenium
Dynamic: author
Dynamic: author-email
Dynamic: classifier
Dynamic: description
Dynamic: description-content-type
Dynamic: home-page
Dynamic: license
Dynamic: license-file
Dynamic: platform
Dynamic: requires-dist
Dynamic: requires-python
Dynamic: summary
